CHANGES.md
MANIFEST.in
README.md
setup.py
mockredis/__init__.py
mockredis/lock.py
mockredis/pipeline.py
mockredis/redis.py
mockredis.egg-info/PKG-INFO
mockredis.egg-info/SOURCES.txt
mockredis.egg-info/dependency_links.txt
mockredis.egg-info/top_level.txt