Metadata-Version: 1.0
Name: mockredis
Version: 0.1.3dev
Summary: A mock redis object.
Home-page: UNKNOWN
Author: UNKNOWN
Author-email: UNKNOWN
License: UNKNOWN
Platform: UNKNOWN
